ai_engine/__init__.py
ai_engine/chitchat.py
ai_engine/dialogue.py
ai_engine/messages.py
ai_engine/types.py
uagents_ai_engine-0.9.0.dist-info/METADATA
uagents_ai_engine-0.9.0.dist-info/WHEEL
uagents_ai_engine-0.9.0.dist-info/RECORD
