Metadata-Version: 2.3
Name: uagents-ai-engine
Version: 0.9.0
Summary: Integrating AI-Engine with UAgents
License: Apache 2.0
Keywords: uagents,agents,ai,ai-engine,fetch.ai
Author: Fetch.AI Limited
Requires-Python: >=3.10,<4.0
Classifier: License :: Other/Proprietary License
Classifier: Programming Language :: Python :: 3
Classifier: Programming Language :: Python :: 3.10
Classifier: Programming Language :: Python :: 3.11
Classifier: Programming Language :: Python :: 3.12
Classifier: Programming Language :: Python :: 3.13
Requires-Dist: pydantic (>=2.8,<3.0)
Requires-Dist: uagents (>=0.21.0,<0.22.0)
